thinhpf/__init__.py
thinhpf/_hpf.cp311-win_amd64.pyd
thinhpf/hpf.py
thinhpf/types.py
thinhpf-0.1.2.dist-info/licenses/LICENSE
thinhpf-0.1.2.dist-info/METADATA
thinhpf-0.1.2.dist-info/WHEEL
thinhpf-0.1.2.dist-info/top_level.txt
thinhpf-0.1.2.dist-info/RECORD
