Metadata-Version: 2.1
Name: thinhpf
Version: 0.1.2
Summary: A thin Python wrapper for the Hochbaum Pseudo Flow (HPF) fast s-t min-cut/max-flow algorithm
Home-page: https://github.com/Skielex/thinhpf
Author: Niels Jeppesen
Author-email: niejep@dtu.dk
Classifier: Development Status :: 3 - Alpha
Classifier: Environment :: Console
Classifier: Intended Audience :: Developers
Classifier: Intended Audience :: Science/Research
Classifier: Natural Language :: English
Classifier: Operating System :: OS Independent
Classifier: Programming Language :: C++
Classifier: Programming Language :: Python
Classifier: Topic :: Scientific/Engineering :: Image Recognition
Classifier: Topic :: Scientific/Engineering :: Artificial Intelligence
Classifier: Topic :: Scientific/Engineering :: Mathematics
License-File: LICENSE
Requires-Dist: numpy
